{
  "id" : 466,
  "expression" : "Collections::emptyMap",
  "projectName" : "keycloak@keycloak",
  "commitID" : "aacae9b9acb0fbedc49d4f88c9fbd7aa11922dce",
  "filePath" : "/model/infinispan/src/main/java/org/keycloak/models/cache/infinispan/authorization/entities/CachedPolicy.java",
  "occurrences" : 1,
  "isArithmeticExpression" : 0,
  "isGetTypeMethod" : 0,
  "expressionList" : [ {
    "nodeContext" : "Collections::emptyMap",
    "nodeType" : "ExpressionMethodReference",
    "nodePosition" : {
      "charLength" : 21,
      "startLineNumber" : 69,
      "startColumnNumber" : 91,
      "endLineNumber" : 69,
      "endColumnNumber" : 112
    },
    "astNodeNumber" : 3,
    "astHeight" : 2,
    "parentDataList" : [ {
      "locationInParent" : "ChildProperty[org.eclipse.jdt.core.dom.Assignment,rightHandSide]",
      "nodePosition" : {
        "charLength" : 91,
        "startLineNumber" : 69,
        "startColumnNumber" : 22,
        "endLineNumber" : 69,
        "endColumnNumber" : 113
      },
      "nodeContext" : "new DefaultLazyLoader<>(source -> new HashMap<>(source.getConfig()),Collections::emptyMap)",
      "nodeType" : "ClassInstanceCreation",
      "astNodeNumber" : 17,
      "astHeight" : 6
    }, {
      "locationInParent" : "ChildProperty[org.eclipse.jdt.core.dom.ExpressionStatement,expression]",
      "nodePosition" : {
        "charLength" : 105,
        "startLineNumber" : 69,
        "startColumnNumber" : 8,
        "endLineNumber" : 69,
        "endColumnNumber" : 113
      },
      "nodeContext" : "this.config=new DefaultLazyLoader<>(source -> new HashMap<>(source.getConfig()),Collections::emptyMap)",
      "nodeType" : "Assignment",
      "astNodeNumber" : 21,
      "astHeight" : 7
    }, {
      "locationInParent" : "ChildListProperty[org.eclipse.jdt.core.dom.Block,statements]",
      "nodePosition" : {
        "charLength" : 106,
        "startLineNumber" : 69,
        "startColumnNumber" : 8,
        "endLineNumber" : 69,
        "endColumnNumber" : 114
      },
      "nodeContext" : "this.config=new DefaultLazyLoader<>(source -> new HashMap<>(source.getConfig()),Collections::emptyMap);\n",
      "nodeType" : "ExpressionStatement",
      "astNodeNumber" : 22,
      "astHeight" : 8
    }, {
      "locationInParent" : "ChildProperty[org.eclipse.jdt.core.dom.MethodDeclaration,body]",
      "nodePosition" : {
        "charLength" : 1014,
        "startLineNumber" : 54,
        "startColumnNumber" : 54,
        "endLineNumber" : 72,
        "endColumnNumber" : 5
      },
      "nodeContext" : "{\n  super(revision,policy.getId());\n  this.type=policy.getType();\n  this.decisionStrategy=policy.getDecisionStrategy();\n  this.logic=policy.getLogic();\n  this.name=policy.getName();\n  this.description=policy.getDescription();\n  this.resourceServerId=policy.getResourceServer().getId();\n  this.associatedPoliciesIds=new DefaultLazyLoader<>(source -> source.getAssociatedPolicies().stream().map(Policy::getId).collect(Collectors.toSet()),Collections::emptySet);\n  this.resourcesIds=new DefaultLazyLoader<>(source -> source.getResources().stream().map(Resource::getId).collect(Collectors.toSet()),Collections::emptySet);\n  this.scopesIds=new DefaultLazyLoader<>(source -> source.getScopes().stream().map(Scope::getId).collect(Collectors.toSet()),Collections::emptySet);\n  this.config=new DefaultLazyLoader<>(source -> new HashMap<>(source.getConfig()),Collections::emptyMap);\n  this.owner=policy.getOwner();\n}\n",
      "nodeType" : "Block",
      "astNodeNumber" : 176,
      "astHeight" : 10
    }, {
      "locationInParent" : "ChildListProperty[org.eclipse.jdt.core.dom.TypeDeclaration,bodyDeclarations]",
      "nodePosition" : {
        "charLength" : 1064,
        "startLineNumber" : 54,
        "startColumnNumber" : 4,
        "endLineNumber" : 72,
        "endColumnNumber" : 5
      },
      "nodeContext" : "public CachedPolicy(Long revision,Policy policy){\n  super(revision,policy.getId());\n  this.type=policy.getType();\n  this.decisionStrategy=policy.getDecisionStrategy();\n  this.logic=policy.getLogic();\n  this.name=policy.getName();\n  this.description=policy.getDescription();\n  this.resourceServerId=policy.getResourceServer().getId();\n  this.associatedPoliciesIds=new DefaultLazyLoader<>(source -> source.getAssociatedPolicies().stream().map(Policy::getId).collect(Collectors.toSet()),Collections::emptySet);\n  this.resourcesIds=new DefaultLazyLoader<>(source -> source.getResources().stream().map(Resource::getId).collect(Collectors.toSet()),Collections::emptySet);\n  this.scopesIds=new DefaultLazyLoader<>(source -> source.getScopes().stream().map(Scope::getId).collect(Collectors.toSet()),Collections::emptySet);\n  this.config=new DefaultLazyLoader<>(source -> new HashMap<>(source.getConfig()),Collections::emptyMap);\n  this.owner=policy.getOwner();\n}\n",
      "nodeType" : "MethodDeclaration",
      "astNodeNumber" : 187,
      "astHeight" : 11
    } ],
    "currentLineData" : {
      "locationInParent" : "ChildListProperty[org.eclipse.jdt.core.dom.Block,statements]",
      "nodePosition" : {
        "charLength" : 106,
        "startLineNumber" : 69,
        "startColumnNumber" : 8,
        "endLineNumber" : 69,
        "endColumnNumber" : 114
      },
      "nodeContext" : "this.config=new DefaultLazyLoader<>(source -> new HashMap<>(source.getConfig()),Collections::emptyMap);\n",
      "nodeType" : "ExpressionStatement",
      "astNodeNumber" : 22,
      "astHeight" : 8
    },
    "tokenLength" : 2,
    "type" : "java.util.function.Supplier<java.util.Map<java.lang.String,java.lang.String>>"
  } ],
  "positionList" : [ {
    "charLength" : 21,
    "startLineNumber" : 69,
    "startColumnNumber" : 91,
    "endLineNumber" : 69,
    "endColumnNumber" : 112
  } ],
  "layoutRelationDataList" : [ ]
}