{
  "id" : 280,
  "expression" : "stubbingFound",
  "projectName" : "mockito@mockito",
  "commitID" : "b9bf63ec9c509d42c485a648c7008a2bc269947d",
  "filePath" : "src/main/java/org/mockito/internal/junit/DefaultStubbingLookupListener.java",
  "occurrences" : 2,
  "isArithmeticExpression" : 0,
  "isGetTypeMethod" : 0,
  "expressionList" : [ {
    "nodeContext" : "stubbingFound",
    "nodeType" : "SimpleName",
    "nodePosition" : {
      "charLength" : 13,
      "startLineNumber" : 35,
      "startColumnNumber" : 110,
      "endLineNumber" : 35,
      "endColumnNumber" : 123
    },
    "astNodeNumber" : 1,
    "astHeight" : 1,
    "parentDataList" : [ {
      "locationInParent" : "ChildProperty[org.eclipse.jdt.core.dom.VariableDeclarationFragment,initializer]",
      "nodePosition" : {
        "charLength" : 86,
        "startLineNumber" : 35,
        "startColumnNumber" : 38,
        "endLineNumber" : 35,
        "endColumnNumber" : 124
      },
      "nodeContext" : "StrictnessSelector.determineStrictness(currentStrictness,mockSettings,stubbingFound)",
      "nodeType" : "MethodInvocation",
      "astNodeNumber" : 6,
      "astHeight" : 2
    }, {
      "locationInParent" : "ChildListProperty[org.eclipse.jdt.core.dom.VariableDeclarationStatement,fragments]",
      "nodePosition" : {
        "charLength" : 105,
        "startLineNumber" : 35,
        "startColumnNumber" : 19,
        "endLineNumber" : 35,
        "endColumnNumber" : 124
      },
      "nodeContext" : "actualStrictness=StrictnessSelector.determineStrictness(currentStrictness,mockSettings,stubbingFound)",
      "nodeType" : "VariableDeclarationFragment",
      "astNodeNumber" : 8,
      "astHeight" : 3
    }, {
      "locationInParent" : "ChildListProperty[org.eclipse.jdt.core.dom.Block,statements]",
      "nodePosition" : {
        "charLength" : 117,
        "startLineNumber" : 35,
        "startColumnNumber" : 8,
        "endLineNumber" : 35,
        "endColumnNumber" : 125
      },
      "nodeContext" : "Strictness actualStrictness=StrictnessSelector.determineStrictness(currentStrictness,mockSettings,stubbingFound);\n",
      "nodeType" : "VariableDeclarationStatement",
      "astNodeNumber" : 11,
      "astHeight" : 4
    }, {
      "locationInParent" : "ChildProperty[org.eclipse.jdt.core.dom.MethodDeclaration,body]",
      "nodePosition" : {
        "charLength" : 1014,
        "startLineNumber" : 34,
        "startColumnNumber" : 115,
        "endLineNumber" : 54,
        "endColumnNumber" : 5
      },
      "nodeContext" : "{\n  Strictness actualStrictness=StrictnessSelector.determineStrictness(currentStrictness,mockSettings,stubbingFound);\n  if (actualStrictness != Strictness.STRICT_STUBS) {\n    return;\n  }\n  if (stubbingFound == null) {\n    List<Invocation> argMismatchStubbings=potentialArgMismatches(invocation);\n    if (!argMismatchStubbings.isEmpty()) {\n      mismatchesReported=true;\n      Reporter.potentialStubbingProblem(invocation,argMismatchStubbings);\n    }\n  }\n else {\n    invocation.markVerified();\n  }\n}\n",
      "nodeType" : "Block",
      "astNodeNumber" : 57,
      "astHeight" : 8
    }, {
      "locationInParent" : "ChildListProperty[org.eclipse.jdt.core.dom.TypeDeclaration,bodyDeclarations]",
      "nodePosition" : {
        "charLength" : 1125,
        "startLineNumber" : 34,
        "startColumnNumber" : 4,
        "endLineNumber" : 54,
        "endColumnNumber" : 5
      },
      "nodeContext" : "public void onStubbingLookup(Invocation invocation,Stubbing stubbingFound,MockCreationSettings mockSettings){\n  Strictness actualStrictness=StrictnessSelector.determineStrictness(currentStrictness,mockSettings,stubbingFound);\n  if (actualStrictness != Strictness.STRICT_STUBS) {\n    return;\n  }\n  if (stubbingFound == null) {\n    List<Invocation> argMismatchStubbings=potentialArgMismatches(invocation);\n    if (!argMismatchStubbings.isEmpty()) {\n      mismatchesReported=true;\n      Reporter.potentialStubbingProblem(invocation,argMismatchStubbings);\n    }\n  }\n else {\n    invocation.markVerified();\n  }\n}\n",
      "nodeType" : "MethodDeclaration",
      "astNodeNumber" : 73,
      "astHeight" : 9
    } ],
    "currentLineData" : {
      "locationInParent" : "ChildListProperty[org.eclipse.jdt.core.dom.Block,statements]",
      "nodePosition" : {
        "charLength" : 117,
        "startLineNumber" : 35,
        "startColumnNumber" : 8,
        "endLineNumber" : 35,
        "endColumnNumber" : 125
      },
      "nodeContext" : "Strictness actualStrictness=StrictnessSelector.determineStrictness(currentStrictness,mockSettings,stubbingFound);\n",
      "nodeType" : "VariableDeclarationStatement",
      "astNodeNumber" : 11,
      "astHeight" : 4
    },
    "tokenLength" : 1,
    "type" : "org.mockito.stubbing.Stubbing"
  }, {
    "nodeContext" : "stubbingFound",
    "nodeType" : "SimpleName",
    "nodePosition" : {
      "charLength" : 13,
      "startLineNumber" : 41,
      "startColumnNumber" : 12,
      "endLineNumber" : 41,
      "endColumnNumber" : 25
    },
    "astNodeNumber" : 1,
    "astHeight" : 1,
    "parentDataList" : [ {
      "locationInParent" : "ChildProperty[org.eclipse.jdt.core.dom.IfStatement,expression]",
      "nodePosition" : {
        "charLength" : 21,
        "startLineNumber" : 41,
        "startColumnNumber" : 12,
        "endLineNumber" : 41,
        "endColumnNumber" : 33
      },
      "nodeContext" : "stubbingFound == null",
      "nodeType" : "InfixExpression",
      "astNodeNumber" : 3,
      "astHeight" : 2
    }, {
      "locationInParent" : "ChildListProperty[org.eclipse.jdt.core.dom.Block,statements]",
      "nodePosition" : {
        "charLength" : 773,
        "startLineNumber" : 41,
        "startColumnNumber" : 8,
        "endLineNumber" : 53,
        "endColumnNumber" : 9
      },
      "nodeContext" : "if (stubbingFound == null) {\n  List<Invocation> argMismatchStubbings=potentialArgMismatches(invocation);\n  if (!argMismatchStubbings.isEmpty()) {\n    mismatchesReported=true;\n    Reporter.potentialStubbingProblem(invocation,argMismatchStubbings);\n  }\n}\n else {\n  invocation.markVerified();\n}\n",
      "nodeType" : "IfStatement",
      "astNodeNumber" : 37,
      "astHeight" : 7
    }, {
      "locationInParent" : "ChildProperty[org.eclipse.jdt.core.dom.MethodDeclaration,body]",
      "nodePosition" : {
        "charLength" : 1014,
        "startLineNumber" : 34,
        "startColumnNumber" : 115,
        "endLineNumber" : 54,
        "endColumnNumber" : 5
      },
      "nodeContext" : "{\n  Strictness actualStrictness=StrictnessSelector.determineStrictness(currentStrictness,mockSettings,stubbingFound);\n  if (actualStrictness != Strictness.STRICT_STUBS) {\n    return;\n  }\n  if (stubbingFound == null) {\n    List<Invocation> argMismatchStubbings=potentialArgMismatches(invocation);\n    if (!argMismatchStubbings.isEmpty()) {\n      mismatchesReported=true;\n      Reporter.potentialStubbingProblem(invocation,argMismatchStubbings);\n    }\n  }\n else {\n    invocation.markVerified();\n  }\n}\n",
      "nodeType" : "Block",
      "astNodeNumber" : 57,
      "astHeight" : 8
    }, {
      "locationInParent" : "ChildListProperty[org.eclipse.jdt.core.dom.TypeDeclaration,bodyDeclarations]",
      "nodePosition" : {
        "charLength" : 1125,
        "startLineNumber" : 34,
        "startColumnNumber" : 4,
        "endLineNumber" : 54,
        "endColumnNumber" : 5
      },
      "nodeContext" : "public void onStubbingLookup(Invocation invocation,Stubbing stubbingFound,MockCreationSettings mockSettings){\n  Strictness actualStrictness=StrictnessSelector.determineStrictness(currentStrictness,mockSettings,stubbingFound);\n  if (actualStrictness != Strictness.STRICT_STUBS) {\n    return;\n  }\n  if (stubbingFound == null) {\n    List<Invocation> argMismatchStubbings=potentialArgMismatches(invocation);\n    if (!argMismatchStubbings.isEmpty()) {\n      mismatchesReported=true;\n      Reporter.potentialStubbingProblem(invocation,argMismatchStubbings);\n    }\n  }\n else {\n    invocation.markVerified();\n  }\n}\n",
      "nodeType" : "MethodDeclaration",
      "astNodeNumber" : 73,
      "astHeight" : 9
    } ],
    "currentLineData" : {
      "locationInParent" : "ChildProperty[org.eclipse.jdt.core.dom.IfStatement,expression]",
      "nodePosition" : {
        "charLength" : 21,
        "startLineNumber" : 41,
        "startColumnNumber" : 12,
        "endLineNumber" : 41,
        "endColumnNumber" : 33
      },
      "nodeContext" : "stubbingFound == null",
      "nodeType" : "InfixExpression",
      "astNodeNumber" : 3,
      "astHeight" : 2
    },
    "tokenLength" : 1,
    "type" : "org.mockito.stubbing.Stubbing"
  } ],
  "positionList" : [ {
    "charLength" : 13,
    "startLineNumber" : 35,
    "startColumnNumber" : 110,
    "endLineNumber" : 35,
    "endColumnNumber" : 123
  }, {
    "charLength" : 13,
    "startLineNumber" : 41,
    "startColumnNumber" : 12,
    "endLineNumber" : 41,
    "endColumnNumber" : 25
  } ],
  "layoutRelationDataList" : [ {
    "firstKey" : 0,
    "secondKey" : 1,
    "layout" : 3
  }, {
    "firstKey" : 1,
    "secondKey" : 0,
    "layout" : 2
  } ]
}