{
  "id" : 276,
  "expression" : "0",
  "projectName" : "quarkusio@quarkus",
  "commitID" : "2862b200ee266332150317795b9fe315be51d68b",
  "filePath" : "/core/test-extension/deployment/src/test/java/io/quarkus/commandmode/PropertyInjectingMain.java",
  "occurrences" : 1,
  "isArithmeticExpression" : 0,
  "isGetTypeMethod" : 0,
  "expressionList" : [ {
    "nodeContext" : "0",
    "nodeType" : "NumberLiteral",
    "nodePosition" : {
      "charLength" : 1,
      "startLineNumber" : 17,
      "startColumnNumber" : 15,
      "endLineNumber" : 17,
      "endColumnNumber" : 16
    },
    "astNodeNumber" : 1,
    "astHeight" : 1,
    "parentDataList" : [ {
      "locationInParent" : "ChildListProperty[org.eclipse.jdt.core.dom.Block,statements]",
      "nodePosition" : {
        "charLength" : 9,
        "startLineNumber" : 17,
        "startColumnNumber" : 8,
        "endLineNumber" : 17,
        "endColumnNumber" : 17
      },
      "nodeContext" : "return 0;\n",
      "nodeType" : "ReturnStatement",
      "astNodeNumber" : 2,
      "astHeight" : 2
    }, {
      "locationInParent" : "ChildProperty[org.eclipse.jdt.core.dom.MethodDeclaration,body]",
      "nodePosition" : {
        "charLength" : 82,
        "startLineNumber" : 15,
        "startColumnNumber" : 35,
        "endLineNumber" : 18,
        "endColumnNumber" : 5
      },
      "nodeContext" : "{\n  System.out.println(\"test.message = \" + message);\n  return 0;\n}\n",
      "nodeType" : "Block",
      "astNodeNumber" : 12,
      "astHeight" : 5
    }, {
      "locationInParent" : "ChildListProperty[org.eclipse.jdt.core.dom.TypeDeclaration,bodyDeclarations]",
      "nodePosition" : {
        "charLength" : 127,
        "startLineNumber" : 14,
        "startColumnNumber" : 4,
        "endLineNumber" : 18,
        "endColumnNumber" : 5
      },
      "nodeContext" : "@Override public int run(String... args){\n  System.out.println(\"test.message = \" + message);\n  return 0;\n}\n",
      "nodeType" : "MethodDeclaration",
      "astNodeNumber" : 22,
      "astHeight" : 6
    } ],
    "currentLineData" : {
      "locationInParent" : "ChildListProperty[org.eclipse.jdt.core.dom.Block,statements]",
      "nodePosition" : {
        "charLength" : 9,
        "startLineNumber" : 17,
        "startColumnNumber" : 8,
        "endLineNumber" : 17,
        "endColumnNumber" : 17
      },
      "nodeContext" : "return 0;\n",
      "nodeType" : "ReturnStatement",
      "astNodeNumber" : 2,
      "astHeight" : 2
    },
    "tokenLength" : 1,
    "type" : "int"
  } ],
  "positionList" : [ {
    "charLength" : 1,
    "startLineNumber" : 17,
    "startColumnNumber" : 15,
    "endLineNumber" : 17,
    "endColumnNumber" : 16
  } ],
  "layoutRelationDataList" : [ ]
}