{
  "id" : 290,
  "expression" : "KeeperState.class",
  "projectName" : "apache@zookeeper",
  "commitID" : "c6639c9842973a7954c8baa412d6825cb833d51f",
  "filePath" : "/src/java/test/org/apache/zookeeper/test/WatchedEventTest.java",
  "occurrences" : 1,
  "isArithmeticExpression" : 0,
  "isGetTypeMethod" : 0,
  "expressionList" : [ {
    "nodeContext" : "KeeperState.class",
    "nodeType" : "TypeLiteral",
    "nodePosition" : {
      "charLength" : 17,
      "startLineNumber" : 39,
      "startColumnNumber" : 54,
      "endLineNumber" : 39,
      "endColumnNumber" : 71
    },
    "astNodeNumber" : 3,
    "astHeight" : 3,
    "parentDataList" : [ {
      "locationInParent" : "ChildProperty[org.eclipse.jdt.core.dom.VariableDeclarationFragment,initializer]",
      "nodePosition" : {
        "charLength" : 32,
        "startLineNumber" : 39,
        "startColumnNumber" : 40,
        "endLineNumber" : 39,
        "endColumnNumber" : 72
      },
      "nodeContext" : "EnumSet.allOf(KeeperState.class)",
      "nodeType" : "MethodInvocation",
      "astNodeNumber" : 6,
      "astHeight" : 4
    }, {
      "locationInParent" : "ChildListProperty[org.eclipse.jdt.core.dom.VariableDeclarationStatement,fragments]",
      "nodePosition" : {
        "charLength" : 44,
        "startLineNumber" : 39,
        "startColumnNumber" : 28,
        "endLineNumber" : 39,
        "endColumnNumber" : 72
      },
      "nodeContext" : "allStates=EnumSet.allOf(KeeperState.class)",
      "nodeType" : "VariableDeclarationFragment",
      "astNodeNumber" : 8,
      "astHeight" : 5
    }, {
      "locationInParent" : "ChildListProperty[org.eclipse.jdt.core.dom.Block,statements]",
      "nodePosition" : {
        "charLength" : 66,
        "startLineNumber" : 39,
        "startColumnNumber" : 7,
        "endLineNumber" : 39,
        "endColumnNumber" : 73
      },
      "nodeContext" : "EnumSet<KeeperState> allStates=EnumSet.allOf(KeeperState.class);\n",
      "nodeType" : "VariableDeclarationStatement",
      "astNodeNumber" : 14,
      "astHeight" : 6
    }, {
      "locationInParent" : "ChildProperty[org.eclipse.jdt.core.dom.MethodDeclaration,body]",
      "nodePosition" : {
        "charLength" : 643,
        "startLineNumber" : 34,
        "startColumnNumber" : 43,
        "endLineNumber" : 51,
        "endColumnNumber" : 5
      },
      "nodeContext" : "{\n  EnumSet<EventType> allTypes=EnumSet.allOf(EventType.class);\n  EnumSet<KeeperState> allStates=EnumSet.allOf(KeeperState.class);\n  WatchedEvent we;\n  for (  EventType et : allTypes) {\n    for (    KeeperState ks : allStates) {\n      we=new WatchedEvent(et,ks,\"blah\");\n      assertEquals(et,we.getType());\n      assertEquals(ks,we.getState());\n      assertEquals(\"blah\",we.getPath());\n    }\n  }\n}\n",
      "nodeType" : "Block",
      "astNodeNumber" : 78,
      "astHeight" : 10
    }, {
      "locationInParent" : "ChildListProperty[org.eclipse.jdt.core.dom.TypeDeclaration,bodyDeclarations]",
      "nodePosition" : {
        "charLength" : 692,
        "startLineNumber" : 33,
        "startColumnNumber" : 4,
        "endLineNumber" : 51,
        "endColumnNumber" : 5
      },
      "nodeContext" : "@Test public void testCreatingWatchedEvent(){\n  EnumSet<EventType> allTypes=EnumSet.allOf(EventType.class);\n  EnumSet<KeeperState> allStates=EnumSet.allOf(KeeperState.class);\n  WatchedEvent we;\n  for (  EventType et : allTypes) {\n    for (    KeeperState ks : allStates) {\n      we=new WatchedEvent(et,ks,\"blah\");\n      assertEquals(et,we.getType());\n      assertEquals(ks,we.getState());\n      assertEquals(\"blah\",we.getPath());\n    }\n  }\n}\n",
      "nodeType" : "MethodDeclaration",
      "astNodeNumber" : 84,
      "astHeight" : 11
    } ],
    "currentLineData" : {
      "locationInParent" : "ChildListProperty[org.eclipse.jdt.core.dom.Block,statements]",
      "nodePosition" : {
        "charLength" : 66,
        "startLineNumber" : 39,
        "startColumnNumber" : 7,
        "endLineNumber" : 39,
        "endColumnNumber" : 73
      },
      "nodeContext" : "EnumSet<KeeperState> allStates=EnumSet.allOf(KeeperState.class);\n",
      "nodeType" : "VariableDeclarationStatement",
      "astNodeNumber" : 14,
      "astHeight" : 6
    },
    "tokenLength" : 1,
    "type" : "java.lang.Class<org.apache.zookeeper.Watcher.Event.KeeperState>"
  } ],
  "positionList" : [ {
    "charLength" : 17,
    "startLineNumber" : 39,
    "startColumnNumber" : 54,
    "endLineNumber" : 39,
    "endColumnNumber" : 71
  } ],
  "layoutRelationDataList" : [ ]
}