{
  "id" : 115,
  "expression" : "\"/index.html\"",
  "projectName" : "openzipkin@zipkin",
  "commitID" : "f02a993656f506277ca83737ddf494ed45fde4b3",
  "filePath" : "/zipkin-server/src/test/java/zipkin2/server/internal/ITZipkinServerQueryDisabled.java",
  "occurrences" : 1,
  "isArithmeticExpression" : 0,
  "isGetTypeMethod" : 0,
  "expressionList" : [ {
    "nodeContext" : "\"/index.html\"",
    "nodeType" : "StringLiteral",
    "nodePosition" : {
      "charLength" : 13,
      "startLineNumber" : 52,
      "startColumnNumber" : 19,
      "endLineNumber" : 52,
      "endColumnNumber" : 32
    },
    "astNodeNumber" : 1,
    "astHeight" : 1,
    "parentDataList" : [ {
      "locationInParent" : "ChildProperty[org.eclipse.jdt.core.dom.MethodInvocation,expression]",
      "nodePosition" : {
        "charLength" : 18,
        "startLineNumber" : 52,
        "startColumnNumber" : 15,
        "endLineNumber" : 52,
        "endColumnNumber" : 33
      },
      "nodeContext" : "get(\"/index.html\")",
      "nodeType" : "MethodInvocation",
      "astNodeNumber" : 3,
      "astHeight" : 2
    }, {
      "locationInParent" : "ChildListProperty[org.eclipse.jdt.core.dom.MethodInvocation,arguments]",
      "nodePosition" : {
        "charLength" : 25,
        "startLineNumber" : 52,
        "startColumnNumber" : 15,
        "endLineNumber" : 52,
        "endColumnNumber" : 40
      },
      "nodeContext" : "get(\"/index.html\").code()",
      "nodeType" : "MethodInvocation",
      "astNodeNumber" : 5,
      "astHeight" : 3
    }, {
      "locationInParent" : "ChildProperty[org.eclipse.jdt.core.dom.MethodInvocation,expression]",
      "nodePosition" : {
        "charLength" : 37,
        "startLineNumber" : 52,
        "startColumnNumber" : 4,
        "endLineNumber" : 52,
        "endColumnNumber" : 41
      },
      "nodeContext" : "assertThat(get(\"/index.html\").code())",
      "nodeType" : "MethodInvocation",
      "astNodeNumber" : 7,
      "astHeight" : 4
    }, {
      "locationInParent" : "ChildProperty[org.eclipse.jdt.core.dom.ExpressionStatement,expression]",
      "nodePosition" : {
        "charLength" : 52,
        "startLineNumber" : 52,
        "startColumnNumber" : 4,
        "endLineNumber" : 52,
        "endColumnNumber" : 56
      },
      "nodeContext" : "assertThat(get(\"/index.html\").code()).isEqualTo(404)",
      "nodeType" : "MethodInvocation",
      "astNodeNumber" : 10,
      "astHeight" : 5
    }, {
      "locationInParent" : "ChildListProperty[org.eclipse.jdt.core.dom.Block,statements]",
      "nodePosition" : {
        "charLength" : 53,
        "startLineNumber" : 52,
        "startColumnNumber" : 4,
        "endLineNumber" : 52,
        "endColumnNumber" : 57
      },
      "nodeContext" : "assertThat(get(\"/index.html\").code()).isEqualTo(404);\n",
      "nodeType" : "ExpressionStatement",
      "astNodeNumber" : 11,
      "astHeight" : 6
    }, {
      "locationInParent" : "ChildProperty[org.eclipse.jdt.core.dom.MethodDeclaration,body]",
      "nodePosition" : {
        "charLength" : 215,
        "startLineNumber" : 50,
        "startColumnNumber" : 64,
        "endLineNumber" : 56,
        "endColumnNumber" : 3
      },
      "nodeContext" : "{\n  assertThat(get(\"/api/v2/traces\").code()).isEqualTo(404);\n  assertThat(get(\"/index.html\").code()).isEqualTo(404);\n  assertThat(get(\"/health\").isSuccessful()).isTrue();\n}\n",
      "nodeType" : "Block",
      "astNodeNumber" : 33,
      "astHeight" : 7
    }, {
      "locationInParent" : "ChildListProperty[org.eclipse.jdt.core.dom.TypeDeclaration,bodyDeclarations]",
      "nodePosition" : {
        "charLength" : 277,
        "startLineNumber" : 50,
        "startColumnNumber" : 2,
        "endLineNumber" : 56,
        "endColumnNumber" : 3
      },
      "nodeContext" : "@Test public void queryRelatedEndpoints404() throws Exception {\n  assertThat(get(\"/api/v2/traces\").code()).isEqualTo(404);\n  assertThat(get(\"/index.html\").code()).isEqualTo(404);\n  assertThat(get(\"/health\").isSuccessful()).isTrue();\n}\n",
      "nodeType" : "MethodDeclaration",
      "astNodeNumber" : 41,
      "astHeight" : 8
    } ],
    "currentLineData" : {
      "locationInParent" : "ChildListProperty[org.eclipse.jdt.core.dom.Block,statements]",
      "nodePosition" : {
        "charLength" : 53,
        "startLineNumber" : 52,
        "startColumnNumber" : 4,
        "endLineNumber" : 52,
        "endColumnNumber" : 57
      },
      "nodeContext" : "assertThat(get(\"/index.html\").code()).isEqualTo(404);\n",
      "nodeType" : "ExpressionStatement",
      "astNodeNumber" : 11,
      "astHeight" : 6
    },
    "tokenLength" : 2,
    "type" : "java.lang.String"
  } ],
  "positionList" : [ {
    "charLength" : 13,
    "startLineNumber" : 52,
    "startColumnNumber" : 19,
    "endLineNumber" : 52,
    "endColumnNumber" : 32
  } ],
  "layoutRelationDataList" : [ ]
}